sintetic_library/__init__.py
sintetic_library/core.py
sintetic_library-0.4.0.dist-info/METADATA
sintetic_library-0.4.0.dist-info/WHEEL
sintetic_library-0.4.0.dist-info/top_level.txt
sintetic_library-0.4.0.dist-info/RECORD
