Metadata-Version: 2.4
Name: sintetic_library
Version: 0.4.0
Summary: Python client for Sintetic Project. This library provides a simple interface to interact with the Sintetic API, allowing users to manage and retrieve data related to synthetic datasets. For more information, visit https://sinteticproject.eu/
Author-email: Leandro Rocchi <leandro.rocchi@cnr.it>
Project-URL: Homepage, https://github.com/n3tmaster/sintetic_library
Project-URL: Bug Tracker, https://github.com/n3tmaster/sintetic_library/issues
Classifier: Programming Language :: Python :: 3
Classifier: License :: OSI Approved :: MIT License
Classifier: Operating System :: OS Independent
Classifier: Development Status :: 3 - Alpha
Requires-Python: >=3.6
Requires-Dist: requests>=2.25.0
Requires-Dist: pytz>=2021.1
Provides-Extra: dev
Requires-Dist: pytest>=6.0; extra == "dev"
Requires-Dist: pytest-cov>=2.0; extra == "dev"
Requires-Dist: black>=21.0; extra == "dev"
Requires-Dist: mypy>=0.900; extra == "dev"
